electrox/__init__.py
electrox/electrox.py
electrox/main.py
electrox-1.24.8.dist-info/LICENSE
electrox-1.24.8.dist-info/METADATA
electrox-1.24.8.dist-info/WHEEL
electrox-1.24.8.dist-info/entry_points.txt
electrox-1.24.8.dist-info/top_level.txt
electrox-1.24.8.dist-info/RECORD
